[
  { "level": 1, "category": "과일", "chosung": "ㅅㄱ", "answer": "사과", "hint": "아침에 먹는 ㅇㅇ는 금이라고 해요." },
  { "level": 1, "category": "과일", "chosung": "ㅂㄴㄴ", "answer": "바나나", "hint": "원숭이는 ㅇㅇㅇ를 좋아해요." },
  { "level": 1, "category": "음식", "chosung": "ㄱ", "answer": "김", "hint": "따뜻한 밥을 ㅇ에 싸 먹으면 정말 맛있어요." },
  { "level": 1, "category": "동물", "chosung": "ㄱㅇㅇ", "answer": "고양이", "hint": "ㅇㅇㅇ가 꼬리를 살랑살랑 흔들어요." },
  { "level": 1, "category": "장소", "chosung": "ㅎㄱ", "answer": "학교", "hint": "내일은 ㅇㅇ에 가서 친구들을 만나요." },
  { "level": 2, "category": "물건", "chosung": "ㅎㄷㅍ", "answer": "휴대폰", "hint": "ㅇㅇㅇ으로 할머니께 전화를 드렸어요." },
  { "level": 1, "category": "식물", "chosung": "ㄴㅁ", "answer": "나무", "hint": "숲에는 키가 큰 ㅇㅇ가 아주 많아요." },
  { "level": 2, "category": "직업", "chosung": "ㄱㅊ", "answer": "경찰", "hint": "길을 잃었을 때 ㅇㅇ 아저씨가 도와주셨어요." },
  { "level": 2, "category": "음식", "chosung": "ㄸㅂㅇ", "answer": "떡볶이", "hint": "매콤달콤한 ㅇㅇㅇ는 인기 간식이에요." },
  { "level": 1, "category": "날씨", "chosung": "ㅂ", "answer": "비", "hint": "하늘에서 주룩주룩 ㅇ가 내려요." },
  { "level": 2, "category": "동물", "chosung": "ㄷㄹㅈ", "answer": "다람쥐", "hint": "ㅇㅇㅇ가 도토리를 까먹고 있어요." },
  { "level": 2, "category": "가전", "chosung": "ㄴㅈㄱ", "answer": "냉장고", "hint": "시원한 물을 ㅇㅇㅇ에서 꺼내 마셨어요." },
  { "level": 1, "category": "학용품", "chosung": "ㄱㅊ", "answer": "공책", "hint": "ㅇㅇ에 예쁜 글씨로 일기를 썼어요." },
  { "level": 1, "category": "신체", "chosung": "ㄴ", "answer": "눈", "hint": "ㅇ이 나빠져서 안경을 썼어요." },
  { "level": 3, "category": "탈것", "chosung": "ㅂㅎㄱ", "answer": "비행기", "hint": "ㅇㅇㅇ를 타고 제주도로 여행을 갔어요." },
  { "level": 2, "category": "운동", "chosung": "ㅊㄱ", "answer": "축구", "hint": "운동장에서 친구들과 ㅇㅇ를 했어요." },
  { "level": 2, "category": "날씨", "chosung": "ㅁㅈㄱ", "answer": "무지개", "hint": "비 온 뒤 하늘에 일곱 빛깔 ㅇㅇㅇ가 떴어요." },
  { "level": 3, "category": "직업", "chosung": "ㅅㅂㄱ", "answer": "소방관", "hint": "ㅇㅇㅇ은 불을 끄고 사람을 구해줘요." },
  { "level": 1, "category": "장소", "chosung": "ㄴㅇㅌ", "answer": "놀이터", "hint": "미끄럼틀 타러 ㅇㅇㅇ에 가자." },
  { "level": 2, "category": "물건", "chosung": "ㅇㅅ", "answer": "우산", "hint": "비가 오니까 ㅇㅇ을 꼭 챙기세요." },
  { "level": 3, "category": "악기", "chosung": "ㅍㅇㄴ", "answer": "피아노", "hint": "건반을 눌러서 ㅇㅇㅇ를 연주해요." },
  { "level": 2, "category": "가족", "chosung": "ㅎㅁㄴ", "answer": "할머니", "hint": "시골에 계신 ㅇㅇㅇ 댁에 놀러 갔어요." },
  { "level": 2, "category": "물건", "chosung": "ㄱㅇ", "answer": "거울", "hint": "ㅇㅇ을 보며 머리를 단정하게 빗어요." },
  { "level": 2, "category": "탈것", "chosung": "ㅈㄷㅊ", "answer": "자동차", "hint": "아빠 ㅇㅇㅇ를 타고 마트에 갔어요." },
  { "level": 1, "category": "계절", "chosung": "ㅂ", "answer": "봄", "hint": "따뜻한 ㅇ이 오면 꽃이 피어요." },
  { "level": 2, "category": "동물", "chosung": "ㅎㄹㅇ", "answer": "호랑이", "hint": "동물원에서 무서운 ㅇㅇㅇ를 봤어요." },
  { "level": 2, "category": "음식", "chosung": "ㄹㅁ", "answer": "라면", "hint": "보글보글 끓인 ㅇㅇ은 정말 맛있어요." },
  { "level": 1, "category": "학용품", "chosung": "ㅈㅇㄱ", "answer": "지우개", "hint": "틀린 글씨는 ㅇㅇㅇ로 지워요." },
  { "level": 2, "category": "장소", "chosung": "ㄷㅅㄱ", "answer": "도서관", "hint": "ㅇㅇㅇ에서는 조용히 책을 읽어야 해요." },
  { "level": 1, "category": "자연", "chosung": "ㄷ", "answer": "달", "hint": "밤하늘에 둥근 ㅇ이 떴어요." },
  { "level": 3, "category": "가전", "chosung": "ㅋㅍㅌ", "answer": "컴퓨터", "hint": "ㅇㅇㅇ로 숙제도 하고 게임도 해요." },
  { "level": 1, "category": "의류", "chosung": "ㅂㅈ", "answer": "바지", "hint": "넘어져서 ㅇㅇ 무릎에 흙이 묻었어요." },
  { "level": 1, "category": "식물", "chosung": "ㄲ", "answer": "꽃", "hint": "정원에 예쁜 ㅇ이 활짝 피었어요." },
  { "level": 2, "category": "학용품", "chosung": "ㅋㄹㅍㅅ", "answer": "크레파스", "hint": "ㅇㅇㅇㅇ로 그림을 색칠해요." },
  { "level": 1, "category": "음식", "chosung": "ㅇㅇ", "answer": "우유", "hint": "키가 크려면 ㅇㅇ를 많이 마셔야 해요." },
  { "level": 1, "category": "동물", "chosung": "ㅌㄲ", "answer": "토끼", "hint": "ㅇㅇ는 깡충깡충 잘 뛰어요." },
  { "level": 2, "category": "장소", "chosung": "ㅂㅇ", "answer": "병원", "hint": "배가 아파서 ㅇㅇ에 가서 주사를 맞았어요." },
  { "level": 1, "category": "자연", "chosung": "ㅎ", "answer": "해", "hint": "아침에 동쪽에서 ㅇ가 떠올라요." },
  { "level": 2, "category": "물건", "chosung": "ㅅㄱ", "answer": "시계", "hint": "벽에 걸린 ㅇㅇ를 보고 시간을 확인해요." },
  { "level": 2, "category": "동물", "chosung": "ㅋㄲㄹ", "answer": "코끼리", "hint": "ㅇㅇㅇ는 코가 아주 길어요." },
  { "level": 2, "category": "음식", "chosung": "ㅊㅋ", "answer": "치킨", "hint": "생일 파티 때 맛있는 ㅇㅇ을 먹었어요." },
  { "level": 1, "category": "날씨", "chosung": "ㄴ", "answer": "눈", "hint": "겨울에는 하얀 ㅇ이 내려요." },
  { "level": 2, "category": "가구", "chosung": "ㅊㄷ", "answer": "침대", "hint": "푹신한 ㅇㅇ에 누워 잠을 자요." },
  { "level": 1, "category": "사람", "chosung": "ㅊㄱ", "answer": "친구", "hint": "가장 친한 ㅇㅇ와 비밀 이야기를 했어요." },
  { "level": 3, "category": "국가", "chosung": "ㅌㄱㄱ", "answer": "태극기", "hint": "우리나라 국기는 ㅇㅇㅇ예요." },
  { "level": 1, "category": "과일", "chosung": "ㅍㄷ", "answer": "포도", "hint": "보라색 알맹이가 달린 ㅇㅇ를 먹었어요." },
  { "level": 2, "category": "물건", "chosung": "ㅇㄱ", "answer": "안경", "hint": "칠판이 잘 안 보여서 ㅇㅇ을 썼어요." },
  { "level": 2, "category": "가전", "chosung": "ㅌㄹㅂㅈ", "answer": "텔레비전", "hint": "거실에서 가족들과 ㅇㅇㅇㅇ을 봐요." },
  { "level": 1, "category": "자연", "chosung": "ㅅ", "answer": "산", "hint": "주말에 아빠와 ㅇ에 등산을 갔어요." },
  { "level": 1, "category": "동물", "chosung": "ㄱㄹ", "answer": "기린", "hint": "ㅇㅇ은 목이 아주 긴 동물이에요." },
  { "level": 1, "category": "과일", "chosung": "ㅅㅂ", "answer": "수박", "hint": "여름에는 시원한 ㅇㅇ을 먹어요." },
  { "level": 1, "category": "학용품", "chosung": "ㅇㅍ", "answer": "연필", "hint": "ㅇㅇ을 깎아서 글씨를 써요." },
  { "level": 2, "category": "탈것", "chosung": "ㅈㅈㄱ", "answer": "자전거", "hint": "공원에서 두 발 ㅇㅇㅇ를 탔어요." },
  { "level": 2, "category": "음식", "chosung": "ㅁㄷ", "answer": "만두", "hint": "설날에 떡국에 ㅇㅇ를 넣어 먹었어요." },
  { "level": 1, "category": "학용품", "chosung": "ㄱㅂ", "answer": "가방", "hint": "학교 갈 때 ㅇㅇ을 메고 가요." },
  { "level": 1, "category": "가족", "chosung": "ㅇㅁ", "answer": "엄마", "hint": "ㅇㅇ가 맛있는 밥을 해주셨어요." },
  { "level": 1, "category": "가족", "chosung": "ㅇㅃ", "answer": "아빠", "hint": "주말에 ㅇㅇ와 공놀이를 했어요." },
  { "level": 2, "category": "직업", "chosung": "ㅇㅅ", "answer": "의사", "hint": "아픈 사람을 치료해 주는 ㅇㅇ 선생님이에요." },
  { "level": 1, "category": "계절", "chosung": "ㅇㄹ", "answer": "여름", "hint": "더운 ㅇㅇ에는 물놀이를 가요." },
  { "level": 1, "category": "계절", "chosung": "ㄱㅇ", "answer": "가을", "hint": "ㅇㅇ에는 단풍이 붉게 물들어요." },
  { "level": 1, "category": "계절", "chosung": "ㄱㅇ", "answer": "겨울", "hint": "추운 ㅇㅇ에는 장갑을 껴야 해요." },
  { "level": 1, "category": "신체", "chosung": "ㅅ", "answer": "손", "hint": "외출하고 돌아오면 ㅇ을 깨끗이 씻어요." },
  { "level": 1, "category": "신체", "chosung": "ㅂ", "answer": "발", "hint": "새 신발을 신으니 ㅇ이 편해요." },
  { "level": 2, "category": "의류", "chosung": "ㅇㅁ", "answer": "양말", "hint": "구멍 난 ㅇㅇ을 꿰매 신었어요." },
  { "level": 2, "category": "의류", "chosung": "ㅁㅈ", "answer": "모자", "hint": "햇볕이 뜨거워서 ㅇㅇ를 썼어요." },
  { "level": 2, "category": "장소", "chosung": "ㅁㅌ", "answer": "마트", "hint": "엄마랑 ㅇㅇ에 가서 장을 봤어요." },
  { "level": 2, "category": "장소", "chosung": "ㅇㄱ", "answer": "약국", "hint": "약사님이 계신 ㅇㅇ에서 밴드를 샀어요." },
  { "level": 3, "category": "탈것", "chosung": "ㄱㅊ", "answer": "기차", "hint": "칙칙폭폭 ㅇㅇ를 타고 할머니 댁에 가요." },
  { "level": 2, "category": "탈것", "chosung": "ㅂㅅ", "answer": "버스", "hint": "정류장에서 ㅇㅇ를 기다려요." },
  { "level": 2, "category": "동물", "chosung": "ㅅㅈ", "answer": "사자", "hint": "갈기가 멋진 ㅇㅇ는 동물의 왕이에요." },
  { "level": 2, "category": "동물", "chosung": "ㄱㅇ", "answer": "고래", "hint": "바다에 사는 커다란 ㅇㅇ를 봤어요." },
  { "level": 2, "category": "음식", "chosung": "ㅍㅈ", "answer": "피자", "hint": "동그란 ㅇㅇ를 한 조각 먹었어요." },
  { "level": 2, "category": "음식", "chosung": "ㅎㅂㄱ", "answer": "햄버거", "hint": "빵 사이에 고기 패티가 들어간 ㅇㅇㅇ예요." },
  { "level": 2, "category": "음식", "chosung": "ㅇㅇㅅㅋㄹ", "answer": "아이스크림", "hint": "더울 때 시원하고 달콤한 ㅇㅇㅇㅇㅇ을 먹어요." },
  { "level": 1, "category": "자연", "chosung": "ㄱㄹ", "answer": "구름", "hint": "하늘에 솜사탕 같은 ㅇㅇ이 떠 있어요." },
  { "level": 1, "category": "자연", "chosung": "ㅂ", "answer": "별", "hint": "밤하늘에 반짝이는 ㅇ을 세어보았어요." },
  { "level": 2, "category": "학교", "chosung": "ㅅㅅㄴ", "answer": "선생님", "hint": "ㅇㅇㅇ 말씀을 잘 들어야 해요." },
  { "level": 2, "category": "학교", "chosung": "ㅊㅍ", "answer": "칠판", "hint": "ㅇㅇ에 분필로 글씨를 써요." },
  { "level": 2, "category": "학교", "chosung": "ㅊㅅ", "answer": "책상", "hint": "ㅇㅇ에 앉아서 공부를 해요." },
  { "level": 2, "category": "학교", "chosung": "ㄱㅅ", "answer": "교실", "hint": "우리 ㅇㅇ은 2층에 있어요." },
  { "level": 2, "category": "물건", "chosung": "ㅊ", "answer": "책", "hint": "도서관에서 재미있는 ㅇ을 빌렸어요." },
  { "level": 2, "category": "물건", "chosung": "ㅋ", "answer": "컵", "hint": "ㅇ에 물을 따라 마셔요." },
  { "level": 2, "category": "물건", "chosung": "ㅎㅈ", "answer": "휴지", "hint": "물 흘린 것을 ㅇㅇ로 닦았어요." },
  { "level": 2, "category": "물건", "chosung": "ㅊㅅㄱ", "answer": "청소기", "hint": "위잉위잉 ㅇㅇㅇ로 먼지를 빨아들여요." },
  { "level": 2, "category": "운동", "chosung": "ㄴㄱ", "answer": "농구", "hint": "공을 던져서 골대에 넣는 ㅇㅇ를 했어요." },
  { "level": 2, "category": "운동", "chosung": "ㅇㄱ", "answer": "야구", "hint": "방망이로 공을 치는 ㅇㅇ 경기를 봤어요." },
  { "level": 2, "category": "운동", "chosung": "ㅌㄱㄷ", "answer": "태권도", "hint": "도장에서 ㅇㅇㅇ를 배워서 띠를 땄어요." },
  { "level": 2, "category": "감정", "chosung": "ㄱㅃ", "answer": "기쁨", "hint": "선물을 받아서 ㅇㅇ의 눈물이 났어요." },
  { "level": 2, "category": "감정", "chosung": "ㅅㅍ", "answer": "슬픔", "hint": "장난감을 잃어버려 ㅇㅇ을 느꼈어요." },
  { "level": 2, "category": "색깔", "chosung": "ㅃㄱ", "answer": "빨강", "hint": "잘 익은 사과는 ㅇㅇ색이에요." },
  { "level": 2, "category": "색깔", "chosung": "ㅍㄹ", "answer": "파랑", "hint": "맑은 하늘은 ㅇㅇ색이에요." },
  { "level": 2, "category": "색깔", "chosung": "ㄴㄹ", "answer": "노랑", "hint": "귀여운 병아리는 ㅇㅇ색이에요." },
  { "level": 2, "category": "동물", "chosung": "ㅇㄹㅁ", "answer": "얼룩말", "hint": "몸에 줄무늬가 있는 ㅇㅇㅇ이 초원을 달려요." },
  { "level": 3, "category": "동물", "chosung": "ㅍㄱ", "answer": "펭귄", "hint": "남극에 사는 뒤뚱뒤뚱 ㅇㅇ을 좋아해요." },
  { "level": 2, "category": "음식", "chosung": "ㄱㅈ", "answer": "과자", "hint": "바삭바삭한 ㅇㅇ를 간식으로 먹었어요." },
  { "level": 2, "category": "음식", "chosung": "ㅅㅌ", "answer": "사탕", "hint": "달콤한 ㅇㅇ을 입에 물고 있어요." },
  { "level": 2, "category": "물건", "chosung": "ㅂㄴ", "answer": "비누", "hint": "ㅇㅇ로 손을 깨끗이 씻어요." },
  { "level": 2, "category": "물건", "chosung": "ㅊㅅ", "answer": "칫솔", "hint": "ㅇㅇ에 치약을 묻혀 양치질해요." },
  { "level": 2, "category": "물건", "chosung": "ㅅㄱ", "answer": "수건", "hint": "세수하고 나서 ㅇㅇ으로 얼굴을 닦아요." }
]